char_picture/__init__.py
char_picture/start.py
char_picture-0.1.3.dist-info/WHEEL
char_picture-0.1.3.dist-info/METADATA
char_picture-0.1.3.dist-info/RECORD
