Metadata-Version: 2.1
Name: char-picture
Version: 0.1.3
Summary: generate char picture demo
Home-page: http://www.qudoor.com/
License: Apache-2.0
Keywords: quamtum,picture
Author: winfred_wu
Author-email: 869286203@qq.com
Maintainer: m1
Maintainer-email: 869286203@qq.com
Requires-Python: >=3.10,<4.0
Classifier: License :: OSI Approved :: Apache Software License
Classifier: Programming Language :: Python :: 3
Classifier: Programming Language :: Python :: 3.10
Requires-Dist: cowpy (>=1.1.5,<2.0.0)
Project-URL: Documentation, https://www.baidu.com/
Project-URL: Repository, http://www.qudoor.com/
